admin_async_upload/__init__.py
admin_async_upload/fields.py
admin_async_upload/files.py
admin_async_upload/models.py
admin_async_upload/storage.py
admin_async_upload/urls.py
admin_async_upload/validators.py
admin_async_upload/views.py
admin_async_upload/widgets.py
admin_async_upload/static/admin_resumable/js/resumable.js
admin_async_upload/templates/admin_resumable/admin_file_input.html
admin_async_upload/templates/admin_resumable/user_file_input.html
django_admin_async_upload-3.0.4.dist-info/LICENSE
django_admin_async_upload-3.0.4.dist-info/METADATA
django_admin_async_upload-3.0.4.dist-info/WHEEL
django_admin_async_upload-3.0.4.dist-info/top_level.txt
django_admin_async_upload-3.0.4.dist-info/RECORD
