Metadata-Version: 2.1
Name: django-admin-async-upload
Version: 3.0.4
Summary: A Django app for the uploading of large files from the django admin site.
Home-page: https://github.com/jonatron/django-admin-resumable-js
Author: Alexey "DataGreed" Strelkov
Author-email: datagreed@gmail.com
License: MIT License
Platform: UNKNOWN
Classifier: Environment :: Web Environment
Classifier: Framework :: Django
Classifier: Intended Audience :: Developers
Classifier: License :: OSI Approved :: MIT License
Classifier: Operating System :: OS Independent
Classifier: Programming Language :: Python
Classifier: Programming Language :: Python :: 2.7
Classifier: Topic :: Internet :: WWW/HTTP
Classifier: Topic :: Internet :: WWW/HTTP :: Dynamic Content
Requires-Dist: Django (>=1.8)
